{
    "fmt": {
        "cargoLocks": null,
        "date": null,
        "extract": null,
        "name": "fmt",
        "passthru": null,
        "pinned": false,
        "src": {
            "deepClone": false,
            "fetchSubmodules": false,
            "leaveDotGit": false,
            "name": null,
            "owner": "fmtlib",
            "repo": "fmt",
            "rev": "11.1.3",
            "sha256": "sha256-6r9D/csVSgS+T/H0J8cSR+YszxnH/h2V2odi2s6VYN8=",
            "sparseCheckout": [],
            "type": "github"
        },
        "version": "11.1.3"
    },
    "reflect-cpp": {
        "cargoLocks": null,
        "date": null,
        "extract": null,
        "name": "reflect-cpp",
        "passthru": null,
        "pinned": false,
        "src": {
            "deepClone": false,
            "fetchSubmodules": false,
            "leaveDotGit": false,
            "name": null,
            "owner": "getml",
            "repo": "reflect-cpp",
            "rev": "v0.17.0",
            "sha256": "sha256-ugMop4Gsw46zFA7mESNzDTAZVzIg3szAX8ND1kUiF2A=",
            "sparseCheckout": [],
            "type": "github"
        },
        "version": "v0.17.0"
    },
    "sdbus-cpp": {
        "cargoLocks": null,
        "date": null,
        "extract": null,
        "name": "sdbus-cpp",
        "passthru": null,
        "pinned": false,
        "src": {
            "deepClone": false,
            "fetchSubmodules": false,
            "leaveDotGit": false,
            "name": null,
            "owner": "kistler-group",
            "repo": "sdbus-cpp",
            "rev": "v2.1.0",
            "sha256": "sha256-JnjabBr7oELLsUV9a+dAAaRyUzaMIriu90vkaVJg2eY=",
            "sparseCheckout": [],
            "type": "github"
        },
        "version": "v2.1.0"
    },
    "tomlplusplus": {
        "cargoLocks": null,
        "date": null,
        "extract": null,
        "name": "tomlplusplus",
        "passthru": null,
        "pinned": false,
        "src": {
            "deepClone": false,
            "fetchSubmodules": false,
            "leaveDotGit": false,
            "name": null,
            "owner": "marzer",
            "repo": "tomlplusplus",
            "rev": "v3.4.0",
            "sha256": "sha256-h5tbO0Rv2tZezY58yUbyRVpsfRjY3i+5TPkkxr6La8M=",
            "sparseCheckout": [],
            "type": "github"
        },
        "version": "v3.4.0"
    },
    "yyjson": {
        "cargoLocks": null,
        "date": null,
        "extract": null,
        "name": "yyjson",
        "passthru": null,
        "pinned": false,
        "src": {
            "deepClone": false,
            "fetchSubmodules": false,
            "leaveDotGit": false,
            "name": null,
            "owner": "ibireme",
            "repo": "yyjson",
            "rev": "0.10.0",
            "sha256": "sha256-mp9Oz08qTyhj3P6F1d81SX96vamUY/JWpD2DTYR+v04=",
            "sparseCheckout": [],
            "type": "github"
        },
        "version": "0.10.0"
    }
}